{
    "name": "Расширения Frame",
    "description": "Менеджер расширений для браузера Frame. Здесь будут отображаться все установленные расширения, а также их информация.",
    "verified": true,
    "scam": false,
    "icon": "icon.png",
    "siteType": "Менеджер расширений",
    "articleUrl": "https://t.me/framebrowserchannel",
    "categories": [
        "сервисы-frame",
        "расширения"
    ],
    "tags": [
        "frame",
        "расширения"
    ],
    "links": {
        "blog": "https://t.me/framebrowserchannel"
    },
    "metadata": {
        "owner": "Kolibra",
        "established": "2026",
        "language": "ru",
        "country": "RU"
    },
    "security": {
        "https": true,
        "certificates": ["Valid SSL"],
        "warnings": []
    },
    "content": {
        "safe": true,
        "adultContent": false,
        "ageRestriction": "0+"
    },
    "analytics": {
        "trackers": ["Google Analytics"],
        "cookies": true
    },
    "lastUpdated": "2026-03-12"
}
